{
    "image":"https://media-exp1.licdn.com/dms/image/C4D03AQHfBga8XCoeag/profile-displayphoto-shrink_800_800/0/1571584199126?e=1632960000&v=beta&t=tBIUW2OR736zdYz74FNInc88rN5NeLmatecaektmffU",
    "nom": "Comte",
    "prenom": "Timothée",
    "date_naissance": "18-07-1998",
    "emplacement": "Région Lyonnaise",
    "description":"Récemment diplômé d'un Bachelor Chef de Projet Informatique, je suis actuellement Chargé de développement Web innovant dans le domaine des réseaux au sein de Orange dans le cadre d'un Master Chef de Projet Ingénierie Logicielle."
}